odoo8_addon_l10n_it_central_journal-8.0.2.0.1-nspkg.pth
odoo_addons/l10n_it_central_journal/README.rst
odoo_addons/l10n_it_central_journal/__init__.py
odoo_addons/l10n_it_central_journal/__openerp__.py
odoo_addons/l10n_it_central_journal/central_journal.py
odoo_addons/l10n_it_central_journal/reports.xml
odoo_addons/l10n_it_central_journal/i18n/it.po
odoo_addons/l10n_it_central_journal/i18n/l10n_it_central_journal.pot
odoo_addons/l10n_it_central_journal/i18n/sl.po
odoo_addons/l10n_it_central_journal/models/__init__.py
odoo_addons/l10n_it_central_journal/models/account.py
odoo_addons/l10n_it_central_journal/static/description/icon.png
odoo_addons/l10n_it_central_journal/views/account_view.xml
odoo_addons/l10n_it_central_journal/views/report_account_central_journal.xml
odoo_addons/l10n_it_central_journal/wizard/__init__.py
odoo_addons/l10n_it_central_journal/wizard/print_giornale.py
odoo_addons/l10n_it_central_journal/wizard/print_giornale.xml
odoo8_addon_l10n_it_central_journal-8.0.2.0.1.dist-info/METADATA
odoo8_addon_l10n_it_central_journal-8.0.2.0.1.dist-info/WHEEL
odoo8_addon_l10n_it_central_journal-8.0.2.0.1.dist-info/namespace_packages.txt
odoo8_addon_l10n_it_central_journal-8.0.2.0.1.dist-info/top_level.txt
odoo8_addon_l10n_it_central_journal-8.0.2.0.1.dist-info/RECORD
