Metadata-Version: 2.1
Name: odoo8-addon-l10n-it-central-journal
Version: 8.0.2.0.1
Summary: Italian Localization - Account central journal
Home-page: http://www.linkgroup.it
Author: Link It Spa, Odoo Community Association (OCA)
Author-email: support@odoo-community.org
License: AGPL-3
Platform: UNKNOWN
Classifier: Programming Language :: Python
Classifier: Framework :: Odoo
Classifier: License :: OSI Approved :: GNU Affero General Public License v3
Requires-Python: ~=2.7
Requires-Dist: odoo8-addon-l10n-it-account
Requires-Dist: odoo (<9.0a,>=8.0a)
